Metadata-Version: 1.1
Name: javasphinx
Version: 0.9.15
Summary: Sphinx extension for documenting Java projects
Home-page: http://github.com/bronto/javasphinx
Author: Chris Thunes
Author-email: cthunes@brewtab.com
License: Apache 2.0
Platform: UNKNOWN
Classifier: Programming Language :: Python
Classifier: Development Status :: 4 - Beta
Classifier: Operating System :: OS Independent
Classifier: License :: OSI Approved :: Apache Software License
Classifier: Intended Audience :: Developers
Classifier: Topic :: Software Development :: Libraries
